snadboy_ssh_docker/README.md
snadboy_ssh_docker/__init__.py
snadboy_ssh_docker/cli.py
snadboy_ssh_docker/client.py
snadboy_ssh_docker/config.py
snadboy_ssh_docker/connection.py
snadboy_ssh_docker/exceptions.py
snadboy_ssh_docker/models.py
snadboy_ssh_docker/ssh_manager.py
snadboy_ssh_docker/utils.py
snadboy_ssh_docker-0.5.0.dist-info/METADATA
snadboy_ssh_docker-0.5.0.dist-info/WHEEL
snadboy_ssh_docker-0.5.0.dist-info/entry_points.txt
snadboy_ssh_docker-0.5.0.dist-info/top_level.txt
snadboy_ssh_docker-0.5.0.dist-info/RECORD
