Metadata-Version: 2.4
Name: snadboy-ssh-docker
Version: 0.5.0
Summary: A Python library for managing Docker containers across multiple remote hosts using Tailscale SSH
Author-email: snadboy <snadboy@example.com>
License-Expression: MIT
Project-URL: Homepage, https://github.com/snadboy/snadboy-ssh-docker
Project-URL: Repository, https://github.com/snadboy/snadboy-ssh-docker
Project-URL: Issues, https://github.com/snadboy/snadboy-ssh-docker/issues
Keywords: docker,ssh,containers,remote,management
Classifier: Development Status :: 4 - Beta
Classifier: Intended Audience :: Developers
Classifier: Programming Language :: Python :: 3
Classifier: Programming Language :: Python :: 3.8
Classifier: Programming Language :: Python :: 3.9
Classifier: Programming Language :: Python :: 3.10
Classifier: Programming Language :: Python :: 3.11
Classifier: Programming Language :: Python :: 3.12
Classifier: Topic :: Software Development :: Libraries :: Python Modules
Classifier: Topic :: System :: Systems Administration
Requires-Python: >=3.8
Requires-Dist: paramiko>=2.7.0
Requires-Dist: pyyaml>=5.4.0
Requires-Dist: pydantic>=2.0.0
Provides-Extra: dev
Requires-Dist: pytest>=6.0; extra == "dev"
Requires-Dist: pytest-asyncio; extra == "dev"
Requires-Dist: pytest-mock; extra == "dev"
Requires-Dist: pytest-cov; extra == "dev"
Requires-Dist: testcontainers; extra == "dev"
Requires-Dist: docker; extra == "dev"
Requires-Dist: black; extra == "dev"
Requires-Dist: isort; extra == "dev"
Requires-Dist: flake8; extra == "dev"
Requires-Dist: mypy; extra == "dev"
